<?xml version="1.0" encoding="windows-1255" standalone="no"?>
<XMD-PAGE REPOSITORY_FORMAT="1.0" PRXML_VER="2.2">
	<Meta ISSUE_DATE="03/01/1908" RELEASE_NO="021-HZT-1908-01-03-001" PAGE_NO="1" NAME="" PAGE_LABEL="1" PAGE_TYPE="Single" PUBLISHER="Olive" PUBLICATION="HZT" SOURCE_TYPE="TIFF" SOURCE_RESOLUTION="72" IMAGES_RESOLUTION="122" PAGE_THUMBNAIL_RESOLUTION="50" PAGE_PREVIEW_RESOLUTION="15" DEFAULT_IMG_EXT="png" IMG_EXT="png" PREVIEW_IMG_EXT="png" XMD_VER="2.6.241.4" PROFILE_ID="W:\Batch\Profile\HZT-1908-01-03.ini" SECTION="Front page" PAGE_WIDTH="505" PAGE_HEIGHT="651" PAGES_NUMBER="8" BASE_HREF="HZT/1908/01/03" PDF_DESTINATION_MAPPED="OLV0_Page_0001" OCR_CONFIDENCE="0.955" TOTAL_CHARS_COUNT="2404" SUSPICIOUS_CHARS_COUNT="82">
		<Resolutions>
			<Resolution DEFAULT="true">50</Resolution>
			<Resolution>69</Resolution>
			<Resolution>120</Resolution>
		</Resolutions>
	</Meta>
	<Link SOURCE="021-HZT-1908-01-03-001.pdf" NEXT_SECTION="2" PREV_SECTION=""/>
	<DataFiles>
		<Files TYPE="DOC_PDF" PRESENT="1"/>
		<Files TYPE="PAGE_PDF" PRESENT="0"/>
		<Files TYPE="DOC_IMG" PRESENT="0"/>
		<Files TYPE="PAGE_IMG" PRESENT="0"/>
		<Files TYPE="PAGE_VIEW_IMG" PRESENT="1"/>
		<Files TYPE="PAGE_PREVIEW_IMG" PRESENT="1"/>
		<Files TYPE="PRIMITIVE_IMG" PRESENT="1"/>
		<Files TYPE="SNIPPET_IMG" PRESENT="1"/>
		<Files TYPE="SEGMENTATION" PRESENT="0"/>
	</DataFiles>
	<Entity ENTITY_TYPE="Article" FIRST_TOC_ENTRY_ID="2" INDEX_IN_DOC="2" DEPTH_LEVEL="1" ID="Ar00100" SIZE="Small" BOX="276 243 471 264" NEXT_SECTION="2" PREV_SECTION="" IMAGES_RESOLUTION="122" TOTAL_CHARS_COUNT="96" SUSPICIOUS_CHARS_COUNT="4" WORDCNT="44">
		<Name>Untitled Article</Name>
		<Primitive ID="Ar0010000" BOX="276 243 471 264" ELEMENT_TYPE="Content" SEQ_NO="0" TOC_ENTRY_ID="2" DEPTH_LEVEL="1"/>
	</Entity>
	<Entity ENTITY_TYPE="Article" FIRST_TOC_ENTRY_ID="4" INDEX_IN_DOC="4" DEPTH_LEVEL="1" ID="Ar00101" SIZE="Large" BOX="265 305 480 591" NEXT_SECTION="2" PREV_SECTION="" IMAGES_RESOLUTION="122" TOTAL_CHARS_COUNT="990" SUSPICIOUS_CHARS_COUNT="38" WORDCNT="322">
		<Name>יריושלס ? ^י</Name>
		<Primitive ID="Ar0010100" BOX="265 305 480 325" ELEMENT_TYPE="HedLine_hl1" SEQ_NO="2" TOC_ENTRY_ID="4" DEPTH_LEVEL="1"/>
		<Primitive ID="Ar0010101" BOX="265 325 480 539" ELEMENT_TYPE="Content" SEQ_NO="0" TOC_ENTRY_ID="4" DEPTH_LEVEL="1"/>
		<Primitive ID="Ar0010102" BOX="266 540 480 591" ELEMENT_TYPE="Content" SEQ_NO="1" TOC_ENTRY_ID="4" DEPTH_LEVEL="1"/>
	</Entity>
	<Entity ENTITY_TYPE="Article" FIRST_TOC_ENTRY_ID="7" INDEX_IN_DOC="7" DEPTH_LEVEL="1" ID="Ar00102" SIZE="Large" BOX="24 275 246 614" NEXT_SECTION="2" PREV_SECTION="" IMAGES_RESOLUTION="122" TOTAL_CHARS_COUNT="1221" SUSPICIOUS_CHARS_COUNT="38" WORDCNT="392">
		<Name>טעלעגראמים</Name>
		<Primitive ID="Ar0010200" BOX="106 275 178 289" ELEMENT_TYPE="HedLine_hl1" SEQ_NO="0" TOC_ENTRY_ID="7" DEPTH_LEVEL="1"/>
		<Primitive ID="Ar0010201" BOX="24 296 246 439" ELEMENT_TYPE="Content" SEQ_NO="1" TOC_ENTRY_ID="7" DEPTH_LEVEL="1"/>
		<Primitive ID="Ar0010202" BOX="26 441 242 614" ELEMENT_TYPE="Content" SEQ_NO="2" TOC_ENTRY_ID="7" DEPTH_LEVEL="1"/>
	</Entity>
	<Entity ENTITY_TYPE="Article" FIRST_TOC_ENTRY_ID="3" INDEX_IN_DOC="3" DEPTH_LEVEL="1" ID="Ar00103" SIZE="Small" BOX="269 275 479 300" NEXT_SECTION="2" PREV_SECTION="" IMAGES_RESOLUTION="122" TOTAL_CHARS_COUNT="97" SUSPICIOUS_CHARS_COUNT="2" WORDCNT="26">
		<Name>Untitled Article</Name>
		<Primitive ID="Ar0010300" BOX="269 275 479 300" ELEMENT_TYPE="Content" SEQ_NO="0" TOC_ENTRY_ID="3" DEPTH_LEVEL="1"/>
	</Entity>
	<Entity ENTITY_TYPE="Ad" FIRST_TOC_ENTRY_ID="1" INDEX_IN_DOC="1" DEPTH_LEVEL="1" ID="Ad00104" SIZE="Small" BOX="365 12 479 119" NEXT_SECTION="2" PREV_SECTION="" IMAGES_RESOLUTION="122" TOTAL_CHARS_COUNT="0" SUSPICIOUS_CHARS_COUNT="0" WORDCNT="93">
		<Name>Untitled Ad</Name>
		<Primitive ID="Ad0010400" BOX="365 12 479 119" ELEMENT_TYPE="Content" SEQ_NO="1" TOC_ENTRY_ID="1" DEPTH_LEVEL="1" E="N"/>
		<Primitive ID="Ad0010401" BOX="365 12 479 119" ELEMENT_TYPE="AdFrame" SEQ_NO="0" TOC_ENTRY_ID="1" DEPTH_LEVEL="1" I_RES="130"/>
	</Entity>
	<Entity ENTITY_TYPE="Ad" FIRST_TOC_ENTRY_ID="5" INDEX_IN_DOC="5" DEPTH_LEVEL="1" ID="Ad00105" SIZE="Small" BOX="34 14 145 121" NEXT_SECTION="2" PREV_SECTION="" IMAGES_RESOLUTION="122" TOTAL_CHARS_COUNT="0" SUSPICIOUS_CHARS_COUNT="0" WORDCNT="84">
		<Name>Untitled Ad</Name>
		<Primitive ID="Ad0010500" BOX="34 14 145 121" ELEMENT_TYPE="Content" SEQ_NO="1" TOC_ENTRY_ID="5" DEPTH_LEVEL="1" E="N"/>
		<Primitive ID="Ad0010501" BOX="34 14 145 121" ELEMENT_TYPE="AdFrame" SEQ_NO="0" TOC_ENTRY_ID="5" DEPTH_LEVEL="1" I_RES="130"/>
	</Entity>
	<Entity ENTITY_TYPE="Ad" FIRST_TOC_ENTRY_ID="6" INDEX_IN_DOC="6" DEPTH_LEVEL="1" ID="Ad00106" SIZE="Small" BOX="33 236 250 269" NEXT_SECTION="2" PREV_SECTION="" IMAGES_RESOLUTION="122" TOTAL_CHARS_COUNT="0" SUSPICIOUS_CHARS_COUNT="0" WORDCNT="37">
		<Name>Untitled Ad</Name>
		<Primitive ID="Ad0010600" BOX="33 236 250 269" ELEMENT_TYPE="Content" SEQ_NO="1" TOC_ENTRY_ID="6" DEPTH_LEVEL="1" E="N"/>
		<Primitive ID="Ad0010601" BOX="33 236 250 269" ELEMENT_TYPE="AdFrame" SEQ_NO="0" TOC_ENTRY_ID="6" DEPTH_LEVEL="1" I_RES="130"/>
	</Entity>
</XMD-PAGE>